aliyunsdkecs/__init__.py
aliyunsdkecs/endpoint.py
aliyunsdkecs/request/__init__.py
aliyunsdkecs/request/v20140526/AcceptInquiredSystemEventRequest.py
aliyunsdkecs/request/v20140526/ActivateRouterInterfaceRequest.py
aliyunsdkecs/request/v20140526/AddBandwidthPackageIpsRequest.py
aliyunsdkecs/request/v20140526/AddTagsRequest.py
aliyunsdkecs/request/v20140526/AllocateDedicatedHostsRequest.py
aliyunsdkecs/request/v20140526/AllocateEipAddressRequest.py
aliyunsdkecs/request/v20140526/AllocatePublicIpAddressRequest.py
aliyunsdkecs/request/v20140526/ApplyAutoSnapshotPolicyRequest.py
aliyunsdkecs/request/v20140526/AssignIpv6AddressesRequest.py
aliyunsdkecs/request/v20140526/AssignPrivateIpAddressesRequest.py
aliyunsdkecs/request/v20140526/AssociateEipAddressRequest.py
aliyunsdkecs/request/v20140526/AssociateHaVipRequest.py
aliyunsdkecs/request/v20140526/AttachClassicLinkVpcRequest.py
aliyunsdkecs/request/v20140526/AttachDiskRequest.py
aliyunsdkecs/request/v20140526/AttachInstanceRamRoleRequest.py
aliyunsdkecs/request/v20140526/AttachKeyPairRequest.py
aliyunsdkecs/request/v20140526/AttachNetworkInterfaceRequest.py
aliyunsdkecs/request/v20140526/AuthorizeSecurityGroupEgressRequest.py
aliyunsdkecs/request/v20140526/AuthorizeSecurityGroupRequest.py
aliyunsdkecs/request/v20140526/CancelAutoSnapshotPolicyRequest.py
aliyunsdkecs/request/v20140526/CancelCopyImageRequest.py
aliyunsdkecs/request/v20140526/CancelImagePipelineExecutionRequest.py
aliyunsdkecs/request/v20140526/CancelPhysicalConnectionRequest.py
aliyunsdkecs/request/v20140526/CancelSimulatedSystemEventsRequest.py
aliyunsdkecs/request/v20140526/CancelTaskRequest.py
aliyunsdkecs/request/v20140526/ConnectRouterInterfaceRequest.py
aliyunsdkecs/request/v20140526/ConvertNatPublicIpToEipRequest.py
aliyunsdkecs/request/v20140526/CopyImageRequest.py
aliyunsdkecs/request/v20140526/CopySnapshotRequest.py
aliyunsdkecs/request/v20140526/CreateActivationRequest.py
aliyunsdkecs/request/v20140526/CreateAutoProvisioningGroupRequest.py
aliyun_python_sdk_ecs-4.24.82.dist-info/LICENSE
aliyun_python_sdk_ecs-4.24.82.dist-info/METADATA
aliyun_python_sdk_ecs-4.24.82.dist-info/WHEEL
aliyun_python_sdk_ecs-4.24.82.dist-info/top_level.txt
aliyun_python_sdk_ecs-4.24.82.dist-info/RECORD
